paper2cmap/__init__.py
paper2cmap/cmapgpt.py
paper2cmap/llm.py
paper2cmap/logger.py
paper2cmap/paper2cmap.py
paper2cmap/paper_reader.py
paper2cmap/metas/generate_examples.json
paper2cmap/metas/merge_and_prune_examples.json
paper2cmap/metas/preprocess_examples.json
paper2cmap/metas/prompts.yaml
paper2cmap-0.1.3.dist-info/LICENSE
paper2cmap-0.1.3.dist-info/METADATA
paper2cmap-0.1.3.dist-info/WHEEL
paper2cmap-0.1.3.dist-info/top_level.txt
paper2cmap-0.1.3.dist-info/RECORD
