Metadata-Version: 2.1
Name: paper2cmap
Version: 0.1.3
Summary: A package that automatically generates a concept map for a PDF document using LLM.
Author-email: weitian <weitian.bnu@gmail.com>
License: MIT License
Project-URL: Homepage, https://github.com/whiskyboy/paper2cmap
Keywords: concept map,cmap,paper,pdf,chatgpt,gpt,llm
Classifier: License :: OSI Approved :: MIT License
Classifier: Programming Language :: Python
Classifier: Programming Language :: Python :: 3
Requires-Python: >=3.8
License-File: LICENSE
Requires-Dist: langchain
Requires-Dist: openai
Requires-Dist: jinja2
Requires-Dist: colorlog
Requires-Dist: PyPDF2
Requires-Dist: pdfminer.six
